environmentalist.py
environmentalist-0.1.1.dist-info/DESCRIPTION.rst
environmentalist-0.1.1.dist-info/METADATA
environmentalist-0.1.1.dist-info/RECORD
environmentalist-0.1.1.dist-info/WHEEL
environmentalist-0.1.1.dist-info/metadata.json
environmentalist-0.1.1.dist-info/top_level.txt
