Metadata-Version: 2.0
Name: environmentalist
Version: 0.1.1
Summary: Accessing environment variables for lazy people.
Home-page: https://github.com/dawran6/100days/tree/master/006
Author: Daw-Ran Liou
Author-email: dawran6@gmail.com
License: MIT
Platform: UNKNOWN
Classifier: Environment :: Console
Classifier: Intended Audience :: Developers
Classifier: Natural Language :: English
Classifier: License :: OSI Approved :: MIT License
Classifier: Programming Language :: Python
Classifier: Programming Language :: Python :: 3
Classifier: Programming Language :: Python :: 3.6
Classifier: Programming Language :: Python :: Implementation :: CPython
Classifier: Topic :: Terminals
